__testpkg__/__init__.py
__testpkg__/test.py
kpy/__init__.py
tests/__init__.py
tests/__testpkg__/__init__.py
tests/__testpkg__/test_test.py
kanimus_py_dev-0.0.4.dist-info/METADATA
kanimus_py_dev-0.0.4.dist-info/WHEEL
kanimus_py_dev-0.0.4.dist-info/top_level.txt
kanimus_py_dev-0.0.4.dist-info/RECORD
